{
  "tenantId": "pg.agranagarnigam",
  "moduleName": "egov-location",
  "TenantBoundary": [
    {
      "hierarchyType": {
        "code": "REVENUE",
        "name": "REVENUE"
      },
      "boundary": {
        "id": 1,
        "boundaryNum": 1,
        "name": "Agra Nagar Nigam",
        "localname": "Agra Nagar Nigam",
        "longitude": null,
        "latitude": null,
        "label": "City",
        "code": "pg.agranagarnigam",
        "children": [
          {
            "id": "94d53dd4-7405-43ef-a5bd-f9d5e0c17a88",
            "boundaryNum": 1,
            "name": "ZONE_1",
            "localname": "ZONE_1",
            "longitude": null,
            "latitude": null,
            "label": "Zone",
            "code": "Z1",
            "children": [
              {
                "id": "db0fff43-8c62-4e23-bce2-38cf3cb142b5",
                "boundaryNum": 1,
                "name": "WARD_1",
                "localname": "WARD_1",
                "longitude": null,
                "latitude": null,
                "label": "Block",
                "code": "W1",
                "children": [
                  {
                    "id": "0db3a9b1-a36d-4a88-a61f-6299d2313584",
                    "boundaryNum": 1,
                    "name": "Agra Nagar Nigam",
                    "localname": "Agra Nagar Nigam",
                    "longitude": null,
                    "latitude": null,
                    "label": "Locality",
                    "code": "L1",
                    "area": "Area1",
                    "children": []
                  }
                ]
              }
            ]
          }
        ]
      }
    }
  ]
}