{
    "tenantId": "pg",
    "moduleName": "BPA",
    "RoomWiseVentilation": [
        {
            "id": 1,
            "occupancy": "residential",
            "permissible": 20,
            "active": true
        },
        {
            "id": 2,
            "occupancy": "commercial",
            "permissible": 25,
            "active": true
        },
        {
            "id": 3,
            "occupancy": "industrial",
            "permissible": 30,
            "active": true
        }
    ]
}